{
    "key": "post_type_6a15806600f53",
    "title": "Soluções",
    "menu_order": 0,
    "active": true,
    "post_type": "solucao",
    "advanced_configuration": true,
    "import_source": "",
    "import_date": "",
    "allow_ai_access": false,
    "ai_description": "",
    "labels": {
        "name": "Soluções",
        "singular_name": "Solução",
        "menu_name": "Soluções",
        "all_items": "Todos os Soluções",
        "edit_item": "Editar Solução",
        "view_item": "Ver Solução",
        "view_items": "Ver Soluções",
        "add_new_item": "Adicionar novo Solução",
        "add_new": "Adicionar novo Solução",
        "new_item": "Novo Solução",
        "parent_item_colon": "Solução ascendente:",
        "search_items": "Pesquisar Soluções",
        "not_found": "Não foi possível encontrar soluções",
        "not_found_in_trash": "Não foi possível encontrar soluções na lixeira",
        "archives": "Arquivos de Solução",
        "attributes": "Atributos de Solução",
        "featured_image": "",
        "set_featured_image": "",
        "remove_featured_image": "",
        "use_featured_image": "",
        "insert_into_item": "Inserir no solução",
        "uploaded_to_this_item": "Enviado para este solução",
        "filter_items_list": "Filtrar lista de soluções",
        "filter_by_date": "Filtrar soluções por data",
        "items_list_navigation": "Navegação na lista de Soluções",
        "items_list": "Lista de Soluções",
        "item_published": "Solução publicado.",
        "item_published_privately": "Solução publicado de forma privada.",
        "item_reverted_to_draft": "Solução revertido para rascunho.",
        "item_scheduled": "Solução agendado.",
        "item_updated": "Solução atualizado.",
        "item_link": "Link de Solução",
        "item_link_description": "Um link para um solução."
    },
    "description": "",
    "public": true,
    "hierarchical": false,
    "exclude_from_search": false,
    "publicly_queryable": true,
    "show_ui": true,
    "show_in_menu": true,
    "admin_menu_parent": "",
    "show_in_admin_bar": true,
    "show_in_nav_menus": true,
    "show_in_rest": true,
    "rest_base": "",
    "rest_namespace": "wp\/v2",
    "rest_controller_class": "WP_REST_Posts_Controller",
    "menu_position": "",
    "menu_icon": {
        "type": "dashicons",
        "value": "dashicons-admin-tools"
    },
    "rename_capabilities": false,
    "singular_capability_name": "post",
    "plural_capability_name": "posts",
    "supports": [
        "title",
        "editor",
        "thumbnail",
        "custom-fields"
    ],
    "taxonomies": "",
    "has_archive": false,
    "has_archive_slug": "",
    "rewrite": {
        "permalink_rewrite": "post_type_key",
        "with_front": "1",
        "feeds": "0",
        "pages": "1"
    },
    "query_var": "post_type_key",
    "query_var_name": "",
    "can_export": true,
    "delete_with_user": false,
    "register_meta_box_cb": "",
    "enter_title_here": "",
    "modified": 1779794047
}
